fustor_source_mysql/__init__.py
fustor_source_mysql/py.typed
fustor_source_mysql-0.2.16.dist-info/METADATA
fustor_source_mysql-0.2.16.dist-info/WHEEL
fustor_source_mysql-0.2.16.dist-info/entry_points.txt
fustor_source_mysql-0.2.16.dist-info/top_level.txt
fustor_source_mysql-0.2.16.dist-info/RECORD
