Metadata-Version: 2.4
Name: fustor-source-mysql
Version: 0.2.16
Summary: A MySQL source for Fustor Agent
Author-email: Huajin Wang <wanghuajin999@163.com>
Requires-Python: >=3.11
Requires-Dist: fustor-core
Requires-Dist: aiomysql>=0.2.0
Requires-Dist: mysql-replication>=1.0.9
Provides-Extra: dev
Requires-Dist: pytest>=8.0.0; extra == "dev"
Requires-Dist: ruff>=0.1.0; extra == "dev"
Requires-Dist: mypy>=1.0.0; extra == "dev"
Requires-Dist: pytest-asyncio>=0.23.0; extra == "dev"
